Metadata-Version: 2.4
Name: bach-prycd_pricing
Version: 1.0.0
Summary: MCP server for accessing Prycd Pricing API
Project-URL: Homepage, https://github.com/bachstudio/bach-prycd_pricing
Project-URL: Repository, https://github.com/bachstudio/bach-prycd_pricing
Project-URL: Documentation, https://github.com/bachstudio/bach-prycd_pricing#readme
Project-URL: Bug Tracker, https://github.com/bachstudio/bach-prycd_pricing/issues
Author: bachstudio
License: MIT License
License-File: LICENSE
Keywords: api,mcp,model-context-protocol,prycd_pricing
Classifier: Development Status :: 4 - Beta
Classifier: Intended Audience :: Developers
Classifier: License :: OSI Approved :: MIT License
Classifier: Programming Language :: Python :: 3
Classifier: Programming Language :: Python :: 3.10
Classifier: Programming Language :: Python :: 3.11
Classifier: Programming Language :: Python :: 3.12
Requires-Python: >=3.10
Requires-Dist: fastmcp>=2.0.0
Requires-Dist: httpx>=0.25.0
Provides-Extra: dev
Requires-Dist: black>=23.0.0; extra == 'dev'
Requires-Dist: pytest>=7.0.0; extra == 'dev'
